LICENSE
MANIFEST.in
README.md
macutil
doc/known_macs.txt
macutil-0.1.21.data/scripts/macutil
macutil-0.1.21.dist-info/METADATA
macutil-0.1.21.dist-info/RECORD
macutil-0.1.21.dist-info/WHEEL
macutil-0.1.21.dist-info/top_level.txt
macutil.egg-info/PKG-INFO
macutil.egg-info/SOURCES.txt
macutil.egg-info/dependency_links.txt
macutil.egg-info/top_level.txt
modules/__init__.py
modules/brute.py
modules/general.py
modules/utility.py
